Metadata-Version: 1.1
Name: sentry-slack-webhooks
Version: 0.3.0
Summary: A Sentry extension which pushes events to the slack incoming webhooks.
Home-page: https://github.com/mtorromeo/sentry-slack-webhooks
Author: Massimiliano Torromeo
Author-email: massimiliano.torromeo@gmail.com
License: BSD
Download-URL: https://github.com/mtorromeo/sentry-slack-webhooks/archive/0.3.0.tar.gz
Platform: UNKNOWN
Classifier: Framework :: Django
Classifier: Intended Audience :: Developers
Classifier: Intended Audience :: System Administrators
Classifier: Operating System :: OS Independent
Classifier: Topic :: Software Development
